django_q2_email_backend/__init__.py
django_q2_email_backend/apps.py
django_q2_email_backend/backends.py
django_q2_email_backend/py.typed
django_q2_email_backend/typing.py
django_q2_email_backend/utils.py
django_q2_email_backend-2.0.0.dist-info/METADATA
django_q2_email_backend-2.0.0.dist-info/WHEEL
django_q2_email_backend-2.0.0.dist-info/licenses/LICENSE
django_q2_email_backend-2.0.0.dist-info/RECORD
